audclas/tortoise_audio_classifier.py
audclas/modules/audio_mini_encoder.py
audclas/modules/checkpoint.py
audclas/modules/dataset.py
audclas/modules/diffusion.py
audclas/modules/stft.py
audclas-0.0.6.dist-info/LICENSE
audclas-0.0.6.dist-info/METADATA
audclas-0.0.6.dist-info/WHEEL
audclas-0.0.6.dist-info/top_level.txt
audclas-0.0.6.dist-info/RECORD
