Metadata-Version: 2.1
Name: audclas
Version: 0.0.6
Summary: Package that uses extracted audio classification model from neonbjb/DL-Art-School - for filtering fine audio files.
Author-email: Shmart <szprytnyd@gmail.com>
Classifier: Programming Language :: Python :: 3
Classifier: License :: OSI Approved :: MIT License
Classifier: Operating System :: Microsoft :: Windows
Requires-Python: >=3.7
License-File: LICENSE
Requires-Dist: huggingface-hub
Requires-Dist: librosa
Requires-Dist: numpy
Requires-Dist: scipy
Requires-Dist: torch
Requires-Dist: torchaudio
